{
  "n": 274,
  "queue": [
    {
      "score": 55,
      "type": "regulation",
      "name": "복무규정",
      "분류": "3000_인사",
      "검수상태": "미검수",
      "별표": true,
      "미분류": false,
      "인바운드": 48,
      "path": "20_규정원문/3000_인사/3400_복무규정.md"
    },
    {
      "score": 55,
      "type": "regulation",
      "name": "여비규정",
      "분류": "4000_보수·여비",
      "검수상태": "미검수",
      "별표": true,
      "미분류": false,
      "인바운드": 22,
      "path": "20_규정원문/4000_보수·여비/4300_여비규정.md"
    },
    {
      "score": 55,
      "type": "regulation",
      "name": "연구발표 등에 있어서의 윤리 및 진실성 검토기준",
      "분류": "0000_미분류",
      "검수상태": "미검수",
      "별표": true,
      "미분류": true,
      "인바운드": 2,
      "path": "20_규정원문/0000_미분류/연구발표 등에 있어서의 윤리 및 진실성 검토기준.md"
    },
    {
      "score": 55,
      "type": "regulation",
      "name": "연구사업관리규정",
      "분류": "5000_연구·정보",
      "검수상태": "미검수",
      "별표": true,
      "미분류": false,
      "인바운드": 16,
      "path": "20_규정원문/5000_연구·정보/5100_연구사업관리규정.md"
    },
    {
      "score": 55,
      "type": "regulation",
      "name": "연구원규정관리기준",
      "분류": "0000_미분류",
      "검수상태": "미검수",
      "별표": true,
      "미분류": true,
      "인바운드": 2,
      "path": "20_규정원문/0000_미분류/연구원규정관리기준.md"
    },
    {
      "score": 55,
      "type": "regulation",
      "name": "연구윤리규정",
      "분류": "5000_연구·정보",
      "검수상태": "미검수",
      "별표": true,
      "미분류": false,
      "인바운드": 10,
      "path": "20_규정원문/5000_연구·정보/5800_연구윤리규정.md"
    },
    {
      "score": 55,
      "type": "regulation",
      "name": "위탁연구사업 계약업무 기준",
      "분류": "0000_미분류",
      "검수상태": "미검수",
      "별표": true,
      "미분류": true,
      "인바운드": 2,
      "path": "20_규정원문/0000_미분류/위탁연구사업 계약업무 기준.md"
    },
    {
      "score": 55,
      "type": "regulation",
      "name": "인사규정",
      "분류": "3000_인사",
      "검수상태": "미검수",
      "별표": true,
      "미분류": false,
      "인바운드": 69,
      "path": "20_규정원문/3000_인사/3100_인사규정.md"
    },
    {
      "score": 55,
      "type": "regulation",
      "name": "임금피크제근로시간단축",
      "분류": "0000_미분류",
      "검수상태": "미검수",
      "별표": true,
      "미분류": true,
      "인바운드": 2,
      "path": "20_규정원문/0000_미분류/임금피크제근로시간단축.md"
    },
    {
      "score": 55,
      "type": "regulation",
      "name": "퇴직자전문성활용제도운영규칙",
      "분류": "3000_인사",
      "검수상태": "미검수",
      "별표": true,
      "미분류": false,
      "인바운드": 10,
      "path": "20_규정원문/3000_인사/3240_퇴직자전문성활용제도운영규칙.md"
    },
    {
      "score": 55,
      "type": "regulation",
      "name": "회계규정",
      "분류": "6000_총무·보안·회계",
      "검수상태": "미검수",
      "별표": true,
      "미분류": false,
      "인바운드": 18,
      "path": "20_규정원문/6000_총무·보안·회계/7100_회계규정.md"
    },
    {
      "score": 54,
      "type": "regulation",
      "name": "KEI규정 관리대장 (능률성과급지급)",
      "분류": "0000_미분류",
      "검수상태": "미검수",
      "별표": true,
      "미분류": true,
      "인바운드": 1,
      "path": "20_규정원문/0000_미분류/KEI규정 관리대장 (능률성과급지급).md"
    },
    {
      "score": 54,
      "type": "regulation",
      "name": "KEI연차저축제세부운영기준",
      "분류": "0000_미분류",
      "검수상태": "미검수",
      "별표": true,
      "미분류": true,
      "인바운드": 1,
      "path": "20_규정원문/0000_미분류/KEI연차저축제세부운영기준.md"
    },
    {
      "score": 54,
      "type": "regulation",
      "name": "국외출장 운영 가이드",
      "분류": "0000_미분류",
      "검수상태": "미검수",
      "별표": true,
      "미분류": true,
      "인바운드": 1,
      "path": "20_규정원문/0000_미분류/국외출장 운영 가이드.md"
    },
    {
      "score": 54,
      "type": "regulation",
      "name": "기본연구과제 등 연구사업 평가 및 감수기준",
      "분류": "0000_미분류",
      "검수상태": "미검수",
      "별표": true,
      "미분류": true,
      "인바운드": 1,
      "path": "20_규정원문/0000_미분류/기본연구과제 등 연구사업 평가 및 감수기준.md"
    },
    {
      "score": 54,
      "type": "regulation",
      "name": "법인카드 사용 가이드라인",
      "분류": "0000_미분류",
      "검수상태": "미검수",
      "별표": true,
      "미분류": true,
      "인바운드": 1,
      "path": "20_규정원문/0000_미분류/법인카드 사용 가이드라인.md"
    },
    {
      "score": 54,
      "type": "regulation",
      "name": "연구연수 결과보고서 및 연구연수 성과물 심의·관리 기준",
      "분류": "0000_미분류",
      "검수상태": "미검수",
      "별표": true,
      "미분류": true,
      "인바운드": 1,
      "path": "20_규정원문/0000_미분류/연구연수 결과보고서 및 연구연수 성과물 심의·관리 기준.md"
    },
    {
      "score": 54,
      "type": "regulation",
      "name": "연구원급 신규채용 운영 요령",
      "분류": "0000_미분류",
      "검수상태": "미검수",
      "별표": true,
      "미분류": true,
      "인바운드": 1,
      "path": "20_규정원문/0000_미분류/연구원급 신규채용 운영 요령.md"
    },
    {
      "score": 54,
      "type": "regulation",
      "name": "연구위원급 신규채용 운영 요령",
      "분류": "0000_미분류",
      "검수상태": "미검수",
      "별표": true,
      "미분류": true,
      "인바운드": 1,
      "path": "20_규정원문/0000_미분류/연구위원급 신규채용 운영 요령.md"
    },
    {
      "score": 54,
      "type": "regulation",
      "name": "직원평가규칙",
      "분류": "3000_인사",
      "검수상태": "미검수",
      "별표": true,
      "미분류": false,
      "인바운드": 9,
      "path": "20_규정원문/3000_인사/3210_직원평가규칙.md"
    },
    {
      "score": 54,
      "type": "regulation",
      "name": "직원평가규칙 세부기준",
      "분류": "0000_미분류",
      "검수상태": "미검수",
      "별표": true,
      "미분류": true,
      "인바운드": 1,
      "path": "20_규정원문/0000_미분류/직원평가규칙 세부기준.md"
    },
    {
      "score": 54,
      "type": "regulation",
      "name": "행정·전문직 신규채용 운영 요령",
      "분류": "0000_미분류",
      "검수상태": "미검수",
      "별표": true,
      "미분류": true,
      "인바운드": 1,
      "path": "20_규정원문/0000_미분류/행정·전문직 신규채용 운영 요령.md"
    },
    {
      "score": 54,
      "type": "regulation",
      "name": "환경평가서및검토의견관리지침",
      "분류": "0000_미분류",
      "검수상태": "미검수",
      "별표": true,
      "미분류": true,
      "인바운드": 1,
      "path": "20_규정원문/0000_미분류/환경평가서및검토의견관리지침.md"
    },
    {
      "score": 53,
      "type": "regulation",
      "name": "「위험성평가」실시절차서",
      "분류": "0000_미분류",
      "검수상태": "미검수",
      "별표": true,
      "미분류": true,
      "인바운드": 0,
      "path": "20_규정원문/0000_미분류/「위험성평가」실시절차서.md"
    },
    {
      "score": 53,
      "type": "regulation",
      "name": "공무 항공마일리지 관리 및 활용 요령",
      "분류": "0000_미분류",
      "검수상태": "미검수",
      "별표": true,
      "미분류": true,
      "인바운드": 0,
      "path": "20_규정원문/0000_미분류/공무 항공마일리지 관리 및 활용 요령.md"
    },
    {
      "score": 53,
      "type": "regulation",
      "name": "규정원문_template",
      "분류": "",
      "검수상태": "미검수",
      "별표": true,
      "미분류": true,
      "인바운드": 0,
      "path": "90_관리/_templates/규정원문_template.md"
    },
    {
      "score": 53,
      "type": "regulation",
      "name": "기본연구사업 등 연구과제 선정 및 배분기준",
      "분류": "0000_미분류",
      "검수상태": "미검수",
      "별표": true,
      "미분류": true,
      "인바운드": 0,
      "path": "20_규정원문/0000_미분류/기본연구사업 등 연구과제 선정 및 배분기준.md"
    },
    {
      "score": 53,
      "type": "regulation",
      "name": "목차",
      "분류": "0000_미분류",
      "검수상태": "미검수",
      "별표": true,
      "미분류": true,
      "인바운드": 0,
      "path": "20_규정원문/0000_미분류/목차.md"
    },
    {
      "score": 53,
      "type": "regulation",
      "name": "발간물 보존 기준",
      "분류": "0000_미분류",
      "검수상태": "미검수",
      "별표": true,
      "미분류": true,
      "인바운드": 0,
      "path": "20_규정원문/0000_미분류/발간물 보존 기준.md"
    },
    {
      "score": 53,
      "type": "regulation",
      "name": "보안관리규정",
      "분류": "6000_총무·보안·회계",
      "검수상태": "미검수",
      "별표": true,
      "미분류": false,
      "인바운드": 8,
      "path": "20_규정원문/6000_총무·보안·회계/6500_보안관리규정.md"
    },
    {
      "score": 53,
      "type": "regulation",
      "name": "상조회규약",
      "분류": "0000_미분류",
      "검수상태": "미검수",
      "별표": true,
      "미분류": true,
      "인바운드": 0,
      "path": "20_규정원문/0000_미분류/상조회규약.md"
    },
    {
      "score": 53,
      "type": "regulation",
      "name": "승진등업무처리기준",
      "분류": "0000_미분류",
      "검수상태": "미검수",
      "별표": true,
      "미분류": true,
      "인바운드": 0,
      "path": "20_규정원문/0000_미분류/승진등업무처리기준.md"
    },
    {
      "score": 53,
      "type": "regulation",
      "name": "위탁연구사업비편성및집행·정산가이드라인",
      "분류": "0000_미분류",
      "검수상태": "미검수",
      "별표": true,
      "미분류": true,
      "인바운드": 0,
      "path": "20_규정원문/0000_미분류/위탁연구사업비편성및집행·정산가이드라인.md"
    },
    {
      "score": 53,
      "type": "regulation",
      "name": "육아시간세부운영방안",
      "분류": "0000_미분류",
      "검수상태": "미검수",
      "별표": true,
      "미분류": true,
      "인바운드": 0,
      "path": "20_규정원문/0000_미분류/육아시간세부운영방안.md"
    },
    {
      "score": 53,
      "type": "regulation",
      "name": "인권경영규정",
      "분류": "3000_인사",
      "검수상태": "미검수",
      "별표": true,
      "미분류": false,
      "인바운드": 8,
      "path": "20_규정원문/3000_인사/3600_인권경영규정.md"
    },
    {
      "score": 53,
      "type": "regulation",
      "name": "정관",
      "분류": "1000_기관",
      "검수상태": "미검수",
      "별표": true,
      "미분류": false,
      "인바운드": 8,
      "path": "20_규정원문/1000_기관/1200_정관.md"
    },
    {
      "score": 53,
      "type": "regulation",
      "name": "퇴직자 활용에 관한 가이드라인",
      "분류": "0000_미분류",
      "검수상태": "미검수",
      "별표": true,
      "미분류": true,
      "인바운드": 0,
      "path": "20_규정원문/0000_미분류/퇴직자 활용에 관한 가이드라인.md"
    },
    {
      "score": 53,
      "type": "regulation",
      "name": "퇴직자전문성활용제도운영기준",
      "분류": "0000_미분류",
      "검수상태": "미검수",
      "별표": true,
      "미분류": true,
      "인바운드": 0,
      "path": "20_규정원문/0000_미분류/퇴직자전문성활용제도운영기준.md"
    },
    {
      "score": 53,
      "type": "regulation",
      "name": "학술지 논문 게재료 지원 기준",
      "분류": "0000_미분류",
      "검수상태": "미검수",
      "별표": true,
      "미분류": true,
      "인바운드": 0,
      "path": "20_규정원문/0000_미분류/학술지 논문 게재료 지원 기준.md"
    },
    {
      "score": 53,
      "type": "regulation",
      "name": "휴양시설 운영요령",
      "분류": "0000_미분류",
      "검수상태": "미검수",
      "별표": true,
      "미분류": true,
      "인바운드": 0,
      "path": "20_규정원문/0000_미분류/휴양시설 운영요령.md"
    },
    {
      "score": 52,
      "type": "regulation",
      "name": "직원원외겸직활동지침",
      "분류": "3000_인사",
      "검수상태": "미검수",
      "별표": true,
      "미분류": false,
      "인바운드": 7,
      "path": "20_규정원문/3000_인사/3430_직원원외겸직활동지침.md"
    },
    {
      "score": 52,
      "type": "regulation",
      "name": "퇴직금규정",
      "분류": "4000_보수·여비",
      "검수상태": "미검수",
      "별표": true,
      "미분류": false,
      "인바운드": 7,
      "path": "20_규정원문/4000_보수·여비/4200_퇴직금규정.md"
    },
    {
      "score": 50,
      "type": "regulation",
      "name": "보수규정",
      "분류": "4000_보수·여비",
      "검수상태": "미검수",
      "별표": true,
      "미분류": false,
      "인바운드": 5,
      "path": "20_규정원문/4000_보수·여비/4100_보수규정.md"
    },
    {
      "score": 50,
      "type": "regulation",
      "name": "직제규정",
      "분류": "2000_감사·규정",
      "검수상태": "미검수",
      "별표": true,
      "미분류": false,
      "인바운드": 5,
      "path": "20_규정원문/2000_감사·규정/2100_직제규정.md"
    },
    {
      "score": 49,
      "type": "regulation",
      "name": "승진.전직에관한규칙",
      "분류": "3000_인사",
      "검수상태": "미검수",
      "별표": true,
      "미분류": false,
      "인바운드": 4,
      "path": "20_규정원문/3000_인사/3120_승진.전직에관한규칙.md"
    },
    {
      "score": 49,
      "type": "regulation",
      "name": "연구연수시행규칙",
      "분류": "3000_인사",
      "검수상태": "미검수",
      "별표": true,
      "미분류": false,
      "인바운드": 4,
      "path": "20_규정원문/3000_인사/3190_연구연수시행규칙.md"
    },
    {
      "score": 49,
      "type": "regulation",
      "name": "정보보안 기본지침",
      "분류": "6000_총무·보안·회계",
      "검수상태": "미검수",
      "별표": true,
      "미분류": false,
      "인바운드": 4,
      "path": "20_규정원문/6000_총무·보안·회계/6510_정보보안 기본지침.md"
    },
    {
      "score": 49,
      "type": "regulation",
      "name": "직원대외활동지침",
      "분류": "3000_인사",
      "검수상태": "미검수",
      "별표": true,
      "미분류": false,
      "인바운드": 4,
      "path": "20_규정원문/3000_인사/3440_직원대외활동지침.md"
    },
    {
      "score": 48,
      "type": "regulation",
      "name": "물품 구매.관리 등에 관한 지침",
      "분류": "6000_총무·보안·회계",
      "검수상태": "미검수",
      "별표": true,
      "미분류": false,
      "인바운드": 3,
      "path": "20_규정원문/6000_총무·보안·회계/7130_물품 구매.관리 등에 관한 지침.md"
    },
    {
      "score": 48,
      "type": "regulation",
      "name": "법인카드관리및사용규칙",
      "분류": "6000_총무·보안·회계",
      "검수상태": "미검수",
      "별표": true,
      "미분류": false,
      "인바운드": 3,
      "path": "20_규정원문/6000_총무·보안·회계/7120_법인카드관리및사용규칙.md"
    },
    {
      "score": 48,
      "type": "regulation",
      "name": "연구성과의 출판·홍보규정",
      "분류": "5000_연구·정보",
      "검수상태": "미검수",
      "별표": true,
      "미분류": false,
      "인바운드": 3,
      "path": "20_규정원문/5000_연구·정보/5500_연구성과의 출판·홍보규정.md"
    },
    {
      "score": 48,
      "type": "regulation",
      "name": "위임전결규정",
      "분류": "2000_감사·규정",
      "검수상태": "미검수",
      "별표": true,
      "미분류": false,
      "인바운드": 3,
      "path": "20_규정원문/2000_감사·규정/2300_위임전결규정.md"
    },
    {
      "score": 48,
      "type": "regulation",
      "name": "유연근무제운영규칙",
      "분류": "3000_인사",
      "검수상태": "미검수",
      "별표": true,
      "미분류": false,
      "인바운드": 3,
      "path": "20_규정원문/3000_인사/3410_유연근무제운영규칙.md"
    },
    {
      "score": 48,
      "type": "regulation",
      "name": "제규정관리규정",
      "분류": "2000_감사·규정",
      "검수상태": "미검수",
      "별표": true,
      "미분류": false,
      "인바운드": 3,
      "path": "20_규정원문/2000_감사·규정/2400_제규정관리규정.md"
    },
    {
      "score": 47,
      "type": "regulation",
      "name": "문서평가및정보공개심의회규정",
      "분류": "6000_총무·보안·회계",
      "검수상태": "미검수",
      "별표": true,
      "미분류": false,
      "인바운드": 2,
      "path": "20_규정원문/6000_총무·보안·회계/6200_문서평가및정보공개심의회규정.md"
    },
    {
      "score": 47,
      "type": "regulation",
      "name": "연장근로등관리규칙",
      "분류": "3000_인사",
      "검수상태": "미검수",
      "별표": true,
      "미분류": false,
      "인바운드": 2,
      "path": "20_규정원문/3000_인사/3420_연장근로등관리규칙.md"
    },
    {
      "score": 47,
      "type": "regulation",
      "name": "임시직운용규칙",
      "분류": "3000_인사",
      "검수상태": "미검수",
      "별표": true,
      "미분류": false,
      "인바운드": 2,
      "path": "20_규정원문/3000_인사/3140_임시직운용규칙.md"
    },
    {
      "score": 47,
      "type": "regulation",
      "name": "정관(영문)",
      "분류": "1000_기관",
      "검수상태": "미검수",
      "별표": true,
      "미분류": false,
      "인바운드": 2,
      "path": "20_규정원문/1000_기관/1200_정관(영문).md"
    },
    {
      "score": 46,
      "type": "regulation",
      "name": "개인정보보호지침",
      "분류": "6000_총무·보안·회계",
      "검수상태": "미검수",
      "별표": true,
      "미분류": false,
      "인바운드": 1,
      "path": "20_규정원문/6000_총무·보안·회계/6540_개인정보보호지침.md"
    },
    {
      "score": 46,
      "type": "regulation",
      "name": "공용차량 관리·운영 지침",
      "분류": "6000_총무·보안·회계",
      "검수상태": "미검수",
      "별표": true,
      "미분류": false,
      "인바운드": 1,
      "path": "20_규정원문/6000_총무·보안·회계/7140_공용차량 관리·운영 지침.md"
    },
    {
      "score": 46,
      "type": "regulation",
      "name": "기후변화영향평가서검토및처리등에관한규정",
      "분류": "5000_연구·정보",
      "검수상태": "미검수",
      "별표": true,
      "미분류": false,
      "인바운드": 1,
      "path": "20_규정원문/5000_연구·정보/5220_기후변화영향평가서검토및처리등에관한규정.md"
    },
    {
      "score": 46,
      "type": "regulation",
      "name": "당직및비상근무규정",
      "분류": "6000_총무·보안·회계",
      "검수상태": "미검수",
      "별표": true,
      "미분류": false,
      "인바운드": 1,
      "path": "20_규정원문/6000_총무·보안·회계/6700_당직및비상근무규정.md"
    },
    {
      "score": 46,
      "type": "regulation",
      "name": "명예퇴직수당지급규칙",
      "분류": "4000_보수·여비",
      "검수상태": "미검수",
      "별표": true,
      "미분류": false,
      "인바운드": 1,
      "path": "20_규정원문/4000_보수·여비/4210_명예퇴직수당지급규칙.md"
    },
    {
      "score": 46,
      "type": "regulation",
      "name": "문서관리규정",
      "분류": "6000_총무·보안·회계",
      "검수상태": "미검수",
      "별표": true,
      "미분류": false,
      "인바운드": 1,
      "path": "20_규정원문/6000_총무·보안·회계/6100_문서관리규정.md"
    },
    {
      "score": 46,
      "type": "regulation",
      "name": "상품권 및 기념품 구매·사용·관리에 관한 지침",
      "분류": "6000_총무·보안·회계",
      "검수상태": "미검수",
      "별표": true,
      "미분류": false,
      "인바운드": 1,
      "path": "20_규정원문/6000_총무·보안·회계/7160_상품권 및 기념품 구매·사용·관리에 관한 지침.md"
    },
    {
      "score": 46,
      "type": "regulation",
      "name": "신규채용자재임용평정규칙",
      "분류": "3000_인사",
      "검수상태": "미검수",
      "별표": true,
      "미분류": false,
      "인바운드": 1,
      "path": "20_규정원문/3000_인사/3150_신규채용자재임용평정규칙.md"
    },
    {
      "score": 46,
      "type": "regulation",
      "name": "연봉시행규칙",
      "분류": "4000_보수·여비",
      "검수상태": "미검수",
      "별표": true,
      "미분류": false,
      "인바운드": 1,
      "path": "20_규정원문/4000_보수·여비/4110_연봉시행규칙.md"
    },
    {
      "score": 46,
      "type": "regulation",
      "name": "예산전용지침",
      "분류": "6000_총무·보안·회계",
      "검수상태": "미검수",
      "별표": true,
      "미분류": false,
      "인바운드": 1,
      "path": "20_규정원문/6000_총무·보안·회계/7110_예산전용지침.md"
    },
    {
      "score": 46,
      "type": "regulation",
      "name": "일용직운용지침",
      "분류": "3000_인사",
      "검수상태": "미검수",
      "별표": true,
      "미분류": false,
      "인바운드": 1,
      "path": "20_규정원문/3000_인사/3160_일용직운용지침.md"
    },
    {
      "score": 46,
      "type": "regulation",
      "name": "자금관리운용규정",
      "분류": "6000_총무·보안·회계",
      "검수상태": "미검수",
      "별표": true,
      "미분류": false,
      "인바운드": 1,
      "path": "20_규정원문/6000_총무·보안·회계/7200_자금관리운용규정.md"
    },
    {
      "score": 46,
      "type": "regulation",
      "name": "전산정보시스템운영규정",
      "분류": "5000_연구·정보",
      "검수상태": "미검수",
      "별표": true,
      "미분류": false,
      "인바운드": 1,
      "path": "20_규정원문/5000_연구·정보/5600_전산정보시스템운영규정.md"
    },
    {
      "score": 46,
      "type": "regulation",
      "name": "주의.경고처분에 관한 지침",
      "분류": "3000_인사",
      "검수상태": "미검수",
      "별표": true,
      "미분류": false,
      "인바운드": 1,
      "path": "20_규정원문/3000_인사/3230_주의.경고처분에 관한 지침.md"
    },
    {
      "score": 46,
      "type": "regulation",
      "name": "지리정보자료활용및보안관리규칙",
      "분류": "6000_총무·보안·회계",
      "검수상태": "미검수",
      "별표": true,
      "미분류": false,
      "인바운드": 1,
      "path": "20_규정원문/6000_총무·보안·회계/6520_지리정보자료활용및보안관리규칙.md"
    },
    {
      "score": 46,
      "type": "regulation",
      "name": "직원신규채용규칙",
      "분류": "3000_인사",
      "검수상태": "미검수",
      "별표": true,
      "미분류": false,
      "인바운드": 1,
      "path": "20_규정원문/3000_인사/3110_직원신규채용규칙.md"
    },
    {
      "score": 46,
      "type": "regulation",
      "name": "파견관 파견수당 지급 지침",
      "분류": "4000_보수·여비",
      "검수상태": "미검수",
      "별표": true,
      "미분류": false,
      "인바운드": 1,
      "path": "20_규정원문/4000_보수·여비/4130_파견관 파견수당 지급 지침.md"
    },
    {
      "score": 46,
      "type": "regulation",
      "name": "환경영향평가서검토및처리등에관한규정",
      "분류": "5000_연구·정보",
      "검수상태": "미검수",
      "별표": true,
      "미분류": false,
      "인바운드": 1,
      "path": "20_규정원문/5000_연구·정보/5210_환경영향평가서검토및처리등에관한규정.md"
    },
    {
      "score": 46,
      "type": "regulation",
      "name": "환경정책교육원운영규정",
      "분류": "5000_연구·정보",
      "검수상태": "미검수",
      "별표": true,
      "미분류": false,
      "인바운드": 1,
      "path": "20_규정원문/5000_연구·정보/5300_환경정책교육원운영규정.md"
    },
    {
      "score": 45,
      "type": "regulation",
      "name": "고충처리운영규칙",
      "분류": "3000_인사",
      "검수상태": "미검수",
      "별표": true,
      "미분류": false,
      "인바운드": 0,
      "path": "20_규정원문/3000_인사/3810_고충처리운영규칙.md"
    },
    {
      "score": 45,
      "type": "regulation",
      "name": "공공저작물 관리규정",
      "분류": "5000_연구·정보",
      "검수상태": "미검수",
      "별표": true,
      "미분류": false,
      "인바운드": 0,
      "path": "20_규정원문/5000_연구·정보/5900_공공저작물 관리규정.md"
    },
    {
      "score": 45,
      "type": "regulation",
      "name": "공로연수운영지침",
      "분류": "3000_인사",
      "검수상태": "미검수",
      "별표": true,
      "미분류": false,
      "인바운드": 0,
      "path": "20_규정원문/3000_인사/3200_공로연수운영지침.md"
    },
    {
      "score": 45,
      "type": "regulation",
      "name": "관사관리지침",
      "분류": "6000_총무·보안·회계",
      "검수상태": "미검수",
      "별표": true,
      "미분류": false,
      "인바운드": 0,
      "path": "20_규정원문/6000_총무·보안·회계/7150_관사관리지침.md"
    },
    {
      "score": 45,
      "type": "regulation",
      "name": "국가기후위기적응센터운영규칙",
      "분류": "2000_감사·규정",
      "검수상태": "미검수",
      "별표": true,
      "미분류": false,
      "인바운드": 0,
      "path": "20_규정원문/2000_감사·규정/2110_국가기후위기적응센터운영규칙.md"
    },
    {
      "score": 45,
      "type": "regulation",
      "name": "기록물관리규정",
      "분류": "6000_총무·보안·회계",
      "검수상태": "미검수",
      "별표": true,
      "미분류": false,
      "인바운드": 0,
      "path": "20_규정원문/6000_총무·보안·회계/6120_기록물관리규정.md"
    },
    {
      "score": 45,
      "type": "regulation",
      "name": "내부감사규정",
      "분류": "2000_감사·규정",
      "검수상태": "미검수",
      "별표": true,
      "미분류": false,
      "인바운드": 0,
      "path": "20_규정원문/2000_감사·규정/2200_내부감사규정.md"
    },
    {
      "score": 45,
      "type": "regulation",
      "name": "노사협의회운영규정",
      "분류": "3000_인사",
      "검수상태": "미검수",
      "별표": true,
      "미분류": false,
      "인바운드": 0,
      "path": "20_규정원문/3000_인사/3800_노사협의회운영규정.md"
    },
    {
      "score": 45,
      "type": "regulation",
      "name": "능률성과급 지급지침",
      "분류": "4000_보수·여비",
      "검수상태": "미검수",
      "별표": true,
      "미분류": false,
      "인바운드": 0,
      "path": "20_규정원문/4000_보수·여비/4120_능률성과급 지급지침.md"
    },
    {
      "score": 45,
      "type": "regulation",
      "name": "문서분류및보관.보존규칙",
      "분류": "6000_총무·보안·회계",
      "검수상태": "미검수",
      "별표": true,
      "미분류": false,
      "인바운드": 0,
      "path": "20_규정원문/6000_총무·보안·회계/6110_문서분류및보관.보존규칙.md"
    },
    {
      "score": 45,
      "type": "regulation",
      "name": "서식관리규정",
      "분류": "6000_총무·보안·회계",
      "검수상태": "미검수",
      "별표": true,
      "미분류": false,
      "인바운드": 0,
      "path": "20_규정원문/6000_총무·보안·회계/6400_서식관리규정.md"
    },
    {
      "score": 45,
      "type": "regulation",
      "name": "석좌연구위원등운용규칙",
      "분류": "3000_인사",
      "검수상태": "미검수",
      "별표": true,
      "미분류": false,
      "인바운드": 0,
      "path": "20_규정원문/3000_인사/3130_석좌연구위원등운용규칙.md"
    },
    {
      "score": 45,
      "type": "regulation",
      "name": "성희롱.성폭력및직장내괴롭힘예방규칙",
      "분류": "3000_인사",
      "검수상태": "미검수",
      "별표": true,
      "미분류": false,
      "인바운드": 0,
      "path": "20_규정원문/3000_인사/3610_성희롱.성폭력및직장내괴롭힘예방규칙.md"
    },
    {
      "score": 45,
      "type": "regulation",
      "name": "신분증발급규칙",
      "분류": "6000_총무·보안·회계",
      "검수상태": "미검수",
      "별표": true,
      "미분류": false,
      "인바운드": 0,
      "path": "20_규정원문/6000_총무·보안·회계/6550_신분증발급규칙.md"
    },
    {
      "score": 45,
      "type": "regulation",
      "name": "안전관리규칙",
      "분류": "6000_총무·보안·회계",
      "검수상태": "미검수",
      "별표": true,
      "미분류": false,
      "인바운드": 0,
      "path": "20_규정원문/6000_총무·보안·회계/6610_안전관리규칙.md"
    },
    {
      "score": 45,
      "type": "regulation",
      "name": "안전사고에 관한 책임자 문책지침",
      "분류": "6000_총무·보안·회계",
      "검수상태": "미검수",
      "별표": true,
      "미분류": false,
      "인바운드": 0,
      "path": "20_규정원문/6000_총무·보안·회계/6620_안전사고에 관한 책임자 문책지침.md"
    },
    {
      "score": 45,
      "type": "regulation",
      "name": "연구과제보안관리지침",
      "분류": "6000_총무·보안·회계",
      "검수상태": "미검수",
      "별표": true,
      "미분류": false,
      "인바운드": 0,
      "path": "20_규정원문/6000_총무·보안·회계/6530_연구과제보안관리지침.md"
    },
    {
      "score": 45,
      "type": "regulation",
      "name": "연구운영회의규정",
      "분류": "2000_감사·규정",
      "검수상태": "미검수",
      "별표": true,
      "미분류": false,
      "인바운드": 0,
      "path": "20_규정원문/2000_감사·규정/2500_연구운영회의규정.md"
    },
    {
      "score": 45,
      "type": "regulation",
      "name": "연구활동비 지급 규칙",
      "분류": "4000_보수·여비",
      "검수상태": "미검수",
      "별표": true,
      "미분류": false,
      "인바운드": 0,
      "path": "20_규정원문/4000_보수·여비/4140_연구활동비 지급 규칙.md"
    },
    {
      "score": 45,
      "type": "regulation",
      "name": "웹사이트운영관리규칙",
      "분류": "5000_연구·정보",
      "검수상태": "미검수",
      "별표": true,
      "미분류": false,
      "인바운드": 0,
      "path": "20_규정원문/5000_연구·정보/5610_웹사이트운영관리규칙.md"
    },
    {
      "score": 45,
      "type": "regulation",
      "name": "임직원부동산신규취득제한에관한지침",
      "분류": "3000_인사",
      "검수상태": "미검수",
      "별표": true,
      "미분류": false,
      "인바운드": 0,
      "path": "20_규정원문/3000_인사/3510_임직원부동산신규취득제한에관한지침.md"
    },
    {
      "score": 45,
      "type": "regulation",
      "name": "자체평가위원회운영규정",
      "분류": "2000_감사·규정",
      "검수상태": "미검수",
      "별표": true,
      "미분류": false,
      "인바운드": 0,
      "path": "20_규정원문/2000_감사·규정/2600_자체평가위원회운영규정.md"
    },
    {
      "score": 45,
      "type": "regulation",
      "name": "전문가활용지침",
      "분류": "5000_연구·정보",
      "검수상태": "미검수",
      "별표": true,
      "미분류": false,
      "인바운드": 0,
      "path": "20_규정원문/5000_연구·정보/5110_전문가활용지침.md"
    },
    {
      "score": 45,
      "type": "regulation",
      "name": "정보자료관리규정",
      "분류": "5000_연구·정보",
      "검수상태": "미검수",
      "별표": true,
      "미분류": false,
      "인바운드": 0,
      "path": "20_규정원문/5000_연구·정보/5400_정보자료관리규정.md"
    },
    {
      "score": 45,
      "type": "regulation",
      "name": "정부출연연구기관등의설립ㆍ운영및육성에관한법률(법률)(제18432호)",
      "분류": "1000_기관",
      "검수상태": "미검수",
      "별표": true,
      "미분류": false,
      "인바운드": 0,
      "path": "20_규정원문/1000_기관/1100_정부출연연구기관등의설립ㆍ운영및육성에관한법률(법률)(제18432호).md"
    },
    {
      "score": 45,
      "type": "regulation",
      "name": "정부출연연구기관등의설립ㆍ운영및육성에관한법률시행령(대통령령)(제32447호)",
      "분류": "1000_기관",
      "검수상태": "미검수",
      "별표": true,
      "미분류": false,
      "인바운드": 0,
      "path": "20_규정원문/1000_기관/1110_정부출연연구기관등의설립ㆍ운영및육성에관한법률시행령(대통령령)(제32447호).md"
    },
    {
      "score": 45,
      "type": "regulation",
      "name": "제안제도운영규칙",
      "분류": "3000_인사",
      "검수상태": "미검수",
      "별표": true,
      "미분류": false,
      "인바운드": 0,
      "path": "20_규정원문/3000_인사/3170_제안제도운영규칙.md"
    },
    {
      "score": 45,
      "type": "regulation",
      "name": "직무관련범죄고발지침",
      "분류": "3000_인사",
      "검수상태": "미검수",
      "별표": true,
      "미분류": false,
      "인바운드": 0,
      "path": "20_규정원문/3000_인사/3520_직무관련범죄고발지침.md"
    },
    {
      "score": 45,
      "type": "regulation",
      "name": "직원교육훈련규칙",
      "분류": "3000_인사",
      "검수상태": "미검수",
      "별표": true,
      "미분류": false,
      "인바운드": 0,
      "path": "20_규정원문/3000_인사/3180_직원교육훈련규칙.md"
    },
    {
      "score": 45,
      "type": "regulation",
      "name": "직원포상규칙",
      "분류": "3000_인사",
      "검수상태": "미검수",
      "별표": true,
      "미분류": false,
      "인바운드": 0,
      "path": "20_규정원문/3000_인사/3220_직원포상규칙.md"
    },
    {
      "score": 45,
      "type": "regulation",
      "name": "직인관리규정",
      "분류": "6000_총무·보안·회계",
      "검수상태": "미검수",
      "별표": true,
      "미분류": false,
      "인바운드": 0,
      "path": "20_규정원문/6000_총무·보안·회계/6300_직인관리규정.md"
    },
    {
      "score": 45,
      "type": "regulation",
      "name": "징계처리 관련 정보공개 지침",
      "분류": "3000_인사",
      "검수상태": "미검수",
      "별표": true,
      "미분류": false,
      "인바운드": 0,
      "path": "20_규정원문/3000_인사/3530_징계처리 관련 정보공개 지침.md"
    },
    {
      "score": 45,
      "type": "regulation",
      "name": "학술지발간규정",
      "분류": "5000_연구·정보",
      "검수상태": "미검수",
      "별표": true,
      "미분류": false,
      "인바운드": 0,
      "path": "20_규정원문/5000_연구·정보/5700_학술지발간규정.md"
    },
    {
      "score": 45,
      "type": "regulation",
      "name": "한국환경연구원임직원의이해충돌방지제도운영규정",
      "분류": "3000_인사",
      "검수상태": "미검수",
      "별표": true,
      "미분류": false,
      "인바운드": 0,
      "path": "20_규정원문/3000_인사/3700_한국환경연구원임직원의이해충돌방지제도운영규정.md"
    },
    {
      "score": 45,
      "type": "regulation",
      "name": "한국환경연구원임직원행동강령",
      "분류": "3000_인사",
      "검수상태": "미검수",
      "별표": true,
      "미분류": false,
      "인바운드": 0,
      "path": "20_규정원문/3000_인사/3500_한국환경연구원임직원행동강령.md"
    },
    {
      "score": 35,
      "type": "guide",
      "name": "2024년도 일반사업(사업형) 관리추진계획",
      "분류": "0000_미분류",
      "검수상태": "미검수",
      "별표": true,
      "미분류": true,
      "인바운드": 0,
      "path": "10_업무가이드/0000_미분류/2024년도 일반사업(사업형) 관리추진계획.md"
    },
    {
      "score": 35,
      "type": "guide",
      "name": "기록물관리가이드",
      "분류": "0000_미분류",
      "검수상태": "미검수",
      "별표": true,
      "미분류": true,
      "인바운드": 0,
      "path": "10_업무가이드/0000_미분류/기록물관리가이드.md"
    },
    {
      "score": 35,
      "type": "guide",
      "name": "인권침해 등 신고 및 처리 절차",
      "분류": "0000_미분류",
      "검수상태": "미검수",
      "별표": true,
      "미분류": true,
      "인바운드": 0,
      "path": "10_업무가이드/0000_미분류/인권침해 등 신고 및 처리 절차.md"
    },
    {
      "score": 35,
      "type": "guide",
      "name": "질병휴직가이드라인",
      "분류": "0000_미분류",
      "검수상태": "미검수",
      "별표": true,
      "미분류": true,
      "인바운드": 0,
      "path": "10_업무가이드/0000_미분류/질병휴직가이드라인.md"
    },
    {
      "score": 35,
      "type": "guide",
      "name": "학술행사진행가이드",
      "분류": "0000_미분류",
      "검수상태": "미검수",
      "별표": true,
      "미분류": true,
      "인바운드": 0,
      "path": "10_업무가이드/0000_미분류/학술행사진행가이드.md"
    },
    {
      "score": 27,
      "type": "guide",
      "name": "2024년도 기본연구사업 관리추진계획",
      "분류": "5000_연구·정보",
      "검수상태": "미검수",
      "별표": true,
      "미분류": false,
      "인바운드": 0,
      "path": "10_업무가이드/5000_연구·정보/2024년도 기본연구사업 관리추진계획.md"
    },
    {
      "score": 27,
      "type": "guide",
      "name": "2024년도 수시연구사업 관리추진계획",
      "분류": "5000_연구·정보",
      "검수상태": "미검수",
      "별표": true,
      "미분류": false,
      "인바운드": 0,
      "path": "10_업무가이드/5000_연구·정보/2024년도 수시연구사업 관리추진계획.md"
    },
    {
      "score": 27,
      "type": "guide",
      "name": "2024년도 일반사업(연구형) 관리추진계획",
      "분류": "5000_연구·정보",
      "검수상태": "미검수",
      "별표": true,
      "미분류": false,
      "인바운드": 0,
      "path": "10_업무가이드/5000_연구·정보/2024년도 일반사업(연구형) 관리추진계획.md"
    },
    {
      "score": 27,
      "type": "guide",
      "name": "2024년신입직원을위한KEI길라잡이",
      "분류": "3000_인사",
      "검수상태": "미검수",
      "별표": true,
      "미분류": false,
      "인바운드": 0,
      "path": "10_업무가이드/3000_인사/2024년신입직원을위한KEI길라잡이.md"
    },
    {
      "score": 27,
      "type": "guide",
      "name": "2025년도일용직(아르바이트)활용기준",
      "분류": "3000_인사",
      "검수상태": "미검수",
      "별표": true,
      "미분류": false,
      "인바운드": 0,
      "path": "10_업무가이드/3000_인사/2025년도일용직(아르바이트)활용기준.md"
    },
    {
      "score": 27,
      "type": "guide",
      "name": "KEI갑질근절가이드라인개정",
      "분류": "3000_인사",
      "검수상태": "미검수",
      "별표": true,
      "미분류": false,
      "인바운드": 0,
      "path": "10_업무가이드/3000_인사/KEI갑질근절가이드라인개정.md"
    },
    {
      "score": 27,
      "type": "guide",
      "name": "KEI경조사관련절차안내",
      "분류": "6000_총무·보안·회계",
      "검수상태": "미검수",
      "별표": true,
      "미분류": false,
      "인바운드": 0,
      "path": "10_업무가이드/6000_총무·보안·회계/KEI경조사관련절차안내.md"
    },
    {
      "score": 27,
      "type": "guide",
      "name": "KEI출판업무편람(2023 개정판)",
      "분류": "6000_총무·보안·회계",
      "검수상태": "미검수",
      "별표": true,
      "미분류": false,
      "인바운드": 0,
      "path": "10_업무가이드/6000_총무·보안·회계/KEI출판업무편람(2023 개정판).md"
    },
    {
      "score": 27,
      "type": "guide",
      "name": "KEI휴가의모든것(25.09.)",
      "분류": "3000_인사",
      "검수상태": "미검수",
      "별표": true,
      "미분류": false,
      "인바운드": 0,
      "path": "10_업무가이드/3000_인사/KEI휴가의모든것(25.09.).md"
    },
    {
      "score": 27,
      "type": "guide",
      "name": "[안내] KEI 대외업무관리시스템 사용자 가이드라인 2024",
      "분류": "5000_연구·정보",
      "검수상태": "미검수",
      "별표": true,
      "미분류": false,
      "인바운드": 0,
      "path": "10_업무가이드/5000_연구·정보/[안내] KEI 대외업무관리시스템 사용자 가이드라인 2024.md"
    },
    {
      "score": 27,
      "type": "guide",
      "name": "가족수당지급기준안내사항",
      "분류": "4000_보수·여비",
      "검수상태": "미검수",
      "별표": true,
      "미분류": false,
      "인바운드": 0,
      "path": "10_업무가이드/4000_보수·여비/가족수당지급기준안내사항.md"
    },
    {
      "score": 27,
      "type": "guide",
      "name": "국외출장 운영 가이드",
      "분류": "4000_보수·여비",
      "검수상태": "미검수",
      "별표": true,
      "미분류": false,
      "인바운드": 0,
      "path": "10_업무가이드/4000_보수·여비/국외출장 운영 가이드_2.md"
    },
    {
      "score": 27,
      "type": "guide",
      "name": "기본연구과제 등 연구사업 평가 및 감수기준",
      "분류": "3000_인사",
      "검수상태": "미검수",
      "별표": true,
      "미분류": false,
      "인바운드": 0,
      "path": "10_업무가이드/3000_인사/기본연구과제 등 연구사업 평가 및 감수기준_2.md"
    },
    {
      "score": 27,
      "type": "guide",
      "name": "기본연구사업등고유과제선정및배분요령(24.02.)",
      "분류": "5000_연구·정보",
      "검수상태": "미검수",
      "별표": true,
      "미분류": false,
      "인바운드": 0,
      "path": "10_업무가이드/5000_연구·정보/기본연구사업등고유과제선정및배분요령(24.02.).md"
    },
    {
      "score": 27,
      "type": "guide",
      "name": "대체인력활용심의및채용절차가이드",
      "분류": "3000_인사",
      "검수상태": "미검수",
      "별표": true,
      "미분류": false,
      "인바운드": 0,
      "path": "10_업무가이드/3000_인사/대체인력활용심의및채용절차가이드.md"
    },
    {
      "score": 27,
      "type": "guide",
      "name": "법인카드 사용 가이드라인",
      "분류": "6000_총무·보안·회계",
      "검수상태": "미검수",
      "별표": true,
      "미분류": false,
      "인바운드": 0,
      "path": "10_업무가이드/6000_총무·보안·회계/법인카드 사용 가이드라인_2.md"
    },
    {
      "score": 27,
      "type": "guide",
      "name": "복무관리방안",
      "분류": "3000_인사",
      "검수상태": "미검수",
      "별표": true,
      "미분류": false,
      "인바운드": 0,
      "path": "10_업무가이드/3000_인사/복무관리방안.md"
    },
    {
      "score": 27,
      "type": "guide",
      "name": "수탁연구사업 발주처별 경비 집행 가이드라인(25.12.)",
      "분류": "6000_총무·보안·회계",
      "검수상태": "미검수",
      "별표": true,
      "미분류": false,
      "인바운드": 0,
      "path": "10_업무가이드/6000_총무·보안·회계/수탁연구사업 발주처별 경비 집행 가이드라인(25.12.).md"
    },
    {
      "score": 27,
      "type": "guide",
      "name": "승진등업무처리기준",
      "분류": "3000_인사",
      "검수상태": "미검수",
      "별표": true,
      "미분류": false,
      "인바운드": 0,
      "path": "10_업무가이드/3000_인사/승진등업무처리기준_2.md"
    },
    {
      "score": 27,
      "type": "guide",
      "name": "양식 연구사업관리규정",
      "분류": "5000_연구·정보",
      "검수상태": "미검수",
      "별표": true,
      "미분류": false,
      "인바운드": 0,
      "path": "10_업무가이드/5000_연구·정보/양식 연구사업관리규정.md"
    },
    {
      "score": 27,
      "type": "guide",
      "name": "연구발표등에있어서의윤리및진실성검토기준",
      "분류": "3000_인사",
      "검수상태": "미검수",
      "별표": true,
      "미분류": false,
      "인바운드": 0,
      "path": "10_업무가이드/3000_인사/연구발표등에있어서의윤리및진실성검토기준.md"
    },
    {
      "score": 27,
      "type": "guide",
      "name": "연구연수기간등의여비지급가이드라인(25.03.)",
      "분류": "4000_보수·여비",
      "검수상태": "미검수",
      "별표": true,
      "미분류": false,
      "인바운드": 0,
      "path": "10_업무가이드/4000_보수·여비/연구연수기간등의여비지급가이드라인(25.03.).md"
    },
    {
      "score": 27,
      "type": "guide",
      "name": "연구원규정관리기준",
      "분류": "5000_연구·정보",
      "검수상태": "미검수",
      "별표": true,
      "미분류": false,
      "인바운드": 0,
      "path": "10_업무가이드/5000_연구·정보/연구원규정관리기준_2.md"
    },
    {
      "score": 27,
      "type": "guide",
      "name": "위탁연구계약관리기준",
      "분류": "6000_총무·보안·회계",
      "검수상태": "미검수",
      "별표": true,
      "미분류": false,
      "인바운드": 0,
      "path": "10_업무가이드/6000_총무·보안·회계/위탁연구계약관리기준.md"
    },
    {
      "score": 27,
      "type": "guide",
      "name": "위탁연구사업비편성및집행·정산가이드라인",
      "분류": "5000_연구·정보",
      "검수상태": "미검수",
      "별표": true,
      "미분류": false,
      "인바운드": 0,
      "path": "10_업무가이드/5000_연구·정보/위탁연구사업비편성및집행·정산가이드라인_2.md"
    },
    {
      "score": 27,
      "type": "guide",
      "name": "육아시간세부운영방안",
      "분류": "3000_인사",
      "검수상태": "미검수",
      "별표": true,
      "미분류": false,
      "인바운드": 0,
      "path": "10_업무가이드/3000_인사/육아시간세부운영방안_2.md"
    },
    {
      "score": 27,
      "type": "guide",
      "name": "자율연구시행가이드라인",
      "분류": "5000_연구·정보",
      "검수상태": "미검수",
      "별표": true,
      "미분류": false,
      "인바운드": 0,
      "path": "10_업무가이드/5000_연구·정보/자율연구시행가이드라인.md"
    },
    {
      "score": 27,
      "type": "guide",
      "name": "직원평가규칙 세부기준",
      "분류": "3000_인사",
      "검수상태": "미검수",
      "별표": true,
      "미분류": false,
      "인바운드": 0,
      "path": "10_업무가이드/3000_인사/직원평가규칙 세부기준_2.md"
    },
    {
      "score": 27,
      "type": "guide",
      "name": "퇴직자 활용에 관한 가이드라인",
      "분류": "3000_인사",
      "검수상태": "미검수",
      "별표": true,
      "미분류": false,
      "인바운드": 0,
      "path": "10_업무가이드/3000_인사/퇴직자 활용에 관한 가이드라인_2.md"
    },
    {
      "score": 27,
      "type": "guide",
      "name": "퇴직자전문성활용제도운영기준",
      "분류": "3000_인사",
      "검수상태": "미검수",
      "별표": true,
      "미분류": false,
      "인바운드": 0,
      "path": "10_업무가이드/3000_인사/퇴직자전문성활용제도운영기준_2.md"
    },
    {
      "score": 27,
      "type": "guide",
      "name": "학생인턴을위한KEI길라잡이",
      "분류": "3000_인사",
      "검수상태": "미검수",
      "별표": true,
      "미분류": false,
      "인바운드": 0,
      "path": "10_업무가이드/3000_인사/학생인턴을위한KEI길라잡이.md"
    },
    {
      "score": 27,
      "type": "guide",
      "name": "환경포럼KEI포커스작성안내서2024",
      "분류": "6000_총무·보안·회계",
      "검수상태": "미검수",
      "별표": true,
      "미분류": false,
      "인바운드": 0,
      "path": "10_업무가이드/6000_총무·보안·회계/환경포럼KEI포커스작성안내서2024.md"
    },
    {
      "score": 20,
      "type": "guide",
      "name": "KEI Library Guide",
      "분류": "0000_미분류",
      "검수상태": "미검수",
      "별표": false,
      "미분류": true,
      "인바운드": 0,
      "path": "10_업무가이드/0000_미분류/KEI Library Guide.md"
    },
    {
      "score": 20,
      "type": "guide",
      "name": "대외활동및원외겸직활동가이드라인",
      "분류": "0000_미분류",
      "검수상태": "미검수",
      "별표": false,
      "미분류": true,
      "인바운드": 0,
      "path": "10_업무가이드/0000_미분류/대외활동및원외겸직활동가이드라인.md"
    },
    {
      "score": 20,
      "type": "guide",
      "name": "보도자료작성및배포절차",
      "분류": "0000_미분류",
      "검수상태": "미검수",
      "별표": false,
      "미분류": true,
      "인바운드": 0,
      "path": "10_업무가이드/0000_미분류/보도자료작성및배포절차.md"
    },
    {
      "score": 20,
      "type": "guide",
      "name": "비정규직사전심의실무가이드",
      "분류": "0000_미분류",
      "검수상태": "미검수",
      "별표": false,
      "미분류": true,
      "인바운드": 0,
      "path": "10_업무가이드/0000_미분류/비정규직사전심의실무가이드.md"
    },
    {
      "score": 20,
      "type": "guide",
      "name": "업무가이드_template",
      "분류": "",
      "검수상태": "미검수",
      "별표": false,
      "미분류": true,
      "인바운드": 0,
      "path": "90_관리/_templates/업무가이드_template.md"
    },
    {
      "score": 20,
      "type": "guide",
      "name": "역량강화프로그램시행가이드라인",
      "분류": "0000_미분류",
      "검수상태": "미검수",
      "별표": false,
      "미분류": true,
      "인바운드": 0,
      "path": "10_업무가이드/0000_미분류/역량강화프로그램시행가이드라인.md"
    },
    {
      "score": 20,
      "type": "guide",
      "name": "연차저축제세부운영기준",
      "분류": "0000_미분류",
      "검수상태": "미검수",
      "별표": false,
      "미분류": true,
      "인바운드": 0,
      "path": "10_업무가이드/0000_미분류/연차저축제세부운영기준.md"
    },
    {
      "score": 20,
      "type": "guide",
      "name": "이메일부재중메시지자동답장기능",
      "분류": "0000_미분류",
      "검수상태": "미검수",
      "별표": false,
      "미분류": true,
      "인바운드": 0,
      "path": "10_업무가이드/0000_미분류/이메일부재중메시지자동답장기능.md"
    },
    {
      "score": 20,
      "type": "guide",
      "name": "자료(도서) 구입신청 안내",
      "분류": "0000_미분류",
      "검수상태": "미검수",
      "별표": false,
      "미분류": true,
      "인바운드": 0,
      "path": "10_업무가이드/0000_미분류/자료(도서) 구입신청 안내.md"
    },
    {
      "score": 20,
      "type": "guide",
      "name": "재해대응매뉴얼",
      "분류": "0000_미분류",
      "검수상태": "미검수",
      "별표": false,
      "미분류": true,
      "인바운드": 0,
      "path": "10_업무가이드/0000_미분류/재해대응매뉴얼.md"
    },
    {
      "score": 20,
      "type": "guide",
      "name": "지급신청별주요증빙및FAQ",
      "분류": "0000_미분류",
      "검수상태": "미검수",
      "별표": false,
      "미분류": true,
      "인바운드": 0,
      "path": "10_업무가이드/0000_미분류/지급신청별주요증빙및FAQ.md"
    },
    {
      "score": 20,
      "type": "guide",
      "name": "휴직신청가이드",
      "분류": "0000_미분류",
      "검수상태": "미검수",
      "별표": false,
      "미분류": true,
      "인바운드": 0,
      "path": "10_업무가이드/0000_미분류/휴직신청가이드.md"
    },
    {
      "score": 18,
      "type": "system",
      "name": "ERP 시스템 · 복무관리",
      "분류": "ERP시스템",
      "검수상태": "미검수",
      "별표": false,
      "미분류": false,
      "인바운드": 19,
      "path": "40_시스템/ERP 시스템 · 복무관리.md"
    },
    {
      "score": 18,
      "type": "system",
      "name": "ERP 시스템 · 평가관리",
      "분류": "ERP시스템",
      "검수상태": "미검수",
      "별표": false,
      "미분류": false,
      "인바운드": 10,
      "path": "40_시스템/ERP 시스템 · 평가관리.md"
    },
    {
      "score": 18,
      "type": "system",
      "name": "ERP 시스템 · 회계관리",
      "분류": "ERP시스템",
      "검수상태": "미검수",
      "별표": false,
      "미분류": false,
      "인바운드": 14,
      "path": "40_시스템/ERP 시스템 · 회계관리.md"
    },
    {
      "score": 17,
      "type": "system",
      "name": "ERP 시스템 · 인사관리",
      "분류": "ERP시스템",
      "검수상태": "미검수",
      "별표": false,
      "미분류": false,
      "인바운드": 9,
      "path": "40_시스템/ERP 시스템 · 인사관리.md"
    },
    {
      "score": 16,
      "type": "system",
      "name": "ERP 시스템 개요",
      "분류": "ERP시스템",
      "검수상태": "미검수",
      "별표": false,
      "미분류": false,
      "인바운드": 8,
      "path": "40_시스템/ERP 시스템 개요.md"
    },
    {
      "score": 14,
      "type": "system",
      "name": "ERP 시스템 · 총무관리",
      "분류": "ERP시스템",
      "검수상태": "미검수",
      "별표": false,
      "미분류": false,
      "인바운드": 6,
      "path": "40_시스템/ERP 시스템 · 총무관리.md"
    },
    {
      "score": 14,
      "type": "term",
      "name": "용어_template",
      "분류": "",
      "검수상태": "미검수",
      "별표": false,
      "미분류": true,
      "인바운드": 0,
      "path": "90_관리/_templates/용어_template.md"
    },
    {
      "score": 13,
      "type": "system",
      "name": "ERP 시스템 · 예산관리",
      "분류": "ERP시스템",
      "검수상태": "미검수",
      "별표": false,
      "미분류": false,
      "인바운드": 5,
      "path": "40_시스템/ERP 시스템 · 예산관리.md"
    },
    {
      "score": 12,
      "type": "guide",
      "name": "2023년귀속근로소득연말정산종합안내및FAQ",
      "분류": "4000_보수·여비",
      "검수상태": "미검수",
      "별표": false,
      "미분류": false,
      "인바운드": 0,
      "path": "10_업무가이드/4000_보수·여비/2023년귀속근로소득연말정산종합안내및FAQ.md"
    },
    {
      "score": 12,
      "type": "guide",
      "name": "2025년 KEI 예산운용가이드",
      "분류": "6000_총무·보안·회계",
      "검수상태": "미검수",
      "별표": false,
      "미분류": false,
      "인바운드": 0,
      "path": "10_업무가이드/6000_총무·보안·회계/2025년 KEI 예산운용가이드.md"
    },
    {
      "score": 12,
      "type": "guide",
      "name": "KEI고유과제보고서작성유의사항(최종보고서제출체크리스트확인서)",
      "분류": "5000_연구·정보",
      "검수상태": "미검수",
      "별표": false,
      "미분류": false,
      "인바운드": 0,
      "path": "10_업무가이드/5000_연구·정보/KEI고유과제보고서작성유의사항(최종보고서제출체크리스트확인서).md"
    },
    {
      "score": 12,
      "type": "guide",
      "name": "SecuwaySSLUV2.1한국환경연구원사용자매뉴얼-v2.1.00908",
      "분류": "5000_연구·정보",
      "검수상태": "미검수",
      "별표": false,
      "미분류": false,
      "인바운드": 0,
      "path": "10_업무가이드/5000_연구·정보/SecuwaySSLUV2.1한국환경연구원사용자매뉴얼-v2.1.00908.md"
    },
    {
      "score": 12,
      "type": "guide",
      "name": "비정규직채용절차기준",
      "분류": "3000_인사",
      "검수상태": "미검수",
      "별표": false,
      "미분류": false,
      "인바운드": 0,
      "path": "10_업무가이드/3000_인사/비정규직채용절차기준.md"
    },
    {
      "score": 12,
      "type": "guide",
      "name": "사이버위기대응실무매뉴얼",
      "분류": "6000_총무·보안·회계",
      "검수상태": "미검수",
      "별표": false,
      "미분류": false,
      "인바운드": 0,
      "path": "10_업무가이드/6000_총무·보안·회계/사이버위기대응실무매뉴얼.md"
    },
    {
      "score": 12,
      "type": "guide",
      "name": "수탁위탁연구계약및정산업무흐름도",
      "분류": "6000_총무·보안·회계",
      "검수상태": "미검수",
      "별표": false,
      "미분류": false,
      "인바운드": 0,
      "path": "10_업무가이드/6000_총무·보안·회계/수탁위탁연구계약및정산업무흐름도.md"
    },
    {
      "score": 12,
      "type": "guide",
      "name": "연구비카드(R D)발급·사용·정산가이드",
      "분류": "6000_총무·보안·회계",
      "검수상태": "미검수",
      "별표": false,
      "미분류": false,
      "인바운드": 0,
      "path": "10_업무가이드/6000_총무·보안·회계/연구비카드(R D)발급·사용·정산가이드.md"
    },
    {
      "score": 12,
      "type": "guide",
      "name": "연구실운영비 사용기준",
      "분류": "5000_연구·정보",
      "검수상태": "미검수",
      "별표": false,
      "미분류": false,
      "인바운드": 0,
      "path": "10_업무가이드/5000_연구·정보/연구실운영비 사용기준.md"
    },
    {
      "score": 12,
      "type": "guide",
      "name": "연구원물품구매·관리가이드라인",
      "분류": "6000_총무·보안·회계",
      "검수상태": "미검수",
      "별표": false,
      "미분류": false,
      "인바운드": 0,
      "path": "10_업무가이드/6000_총무·보안·회계/연구원물품구매·관리가이드라인.md"
    },
    {
      "score": 12,
      "type": "guide",
      "name": "연구자료공유를위한스마트연구플랫폼매뉴얼",
      "분류": "5000_연구·정보",
      "검수상태": "미검수",
      "별표": false,
      "미분류": false,
      "인바운드": 0,
      "path": "10_업무가이드/5000_연구·정보/연구자료공유를위한스마트연구플랫폼매뉴얼.md"
    },
    {
      "score": 12,
      "type": "guide",
      "name": "임금피크제근로시간단축",
      "분류": "3000_인사",
      "검수상태": "미검수",
      "별표": false,
      "미분류": false,
      "인바운드": 0,
      "path": "10_업무가이드/3000_인사/임금피크제근로시간단축_2.md"
    },
    {
      "score": 12,
      "type": "guide",
      "name": "임시직연구원채용절차FAQ",
      "분류": "3000_인사",
      "검수상태": "미검수",
      "별표": false,
      "미분류": false,
      "인바운드": 0,
      "path": "10_업무가이드/3000_인사/임시직연구원채용절차FAQ.md"
    },
    {
      "score": 12,
      "type": "guide",
      "name": "정년퇴직예정직원안내사항",
      "분류": "3000_인사",
      "검수상태": "미검수",
      "별표": false,
      "미분류": false,
      "인바운드": 0,
      "path": "10_업무가이드/3000_인사/정년퇴직예정직원안내사항.md"
    },
    {
      "score": 12,
      "type": "guide",
      "name": "포상대상자추천을위한시스템활용법 ppt",
      "분류": "5000_연구·정보",
      "검수상태": "미검수",
      "별표": false,
      "미분류": false,
      "인바운드": 0,
      "path": "10_업무가이드/5000_연구·정보/포상대상자추천을위한시스템활용법 ppt.md"
    },
    {
      "score": 12,
      "type": "guide",
      "name": "행복한KEI직장맘대디길라잡이(25.09.)",
      "분류": "3000_인사",
      "검수상태": "미검수",
      "별표": false,
      "미분류": false,
      "인바운드": 0,
      "path": "10_업무가이드/3000_인사/행복한KEI직장맘대디길라잡이(25.09.).md"
    },
    {
      "score": 12,
      "type": "system",
      "name": "ERP 시스템 · 구매관리",
      "분류": "ERP시스템",
      "검수상태": "미검수",
      "별표": false,
      "미분류": false,
      "인바운드": 4,
      "path": "40_시스템/ERP 시스템 · 구매관리.md"
    },
    {
      "score": 11,
      "type": "system",
      "name": "ERP 시스템 · 급여관리",
      "분류": "ERP시스템",
      "검수상태": "미검수",
      "별표": false,
      "미분류": false,
      "인바운드": 3,
      "path": "40_시스템/ERP 시스템 · 급여관리.md"
    },
    {
      "score": 11,
      "type": "system",
      "name": "ERP 시스템 · 자산관리",
      "분류": "ERP시스템",
      "검수상태": "미검수",
      "별표": false,
      "미분류": false,
      "인바운드": 3,
      "path": "40_시스템/ERP 시스템 · 자산관리.md"
    },
    {
      "score": 10,
      "type": "system",
      "name": "ERP 시스템 · 경영지원",
      "분류": "ERP시스템",
      "검수상태": "미검수",
      "별표": false,
      "미분류": false,
      "인바운드": 2,
      "path": "40_시스템/ERP 시스템 · 경영지원.md"
    },
    {
      "score": 9,
      "type": "system",
      "name": "ERP 시스템 · 경영자정보",
      "분류": "ERP시스템",
      "검수상태": "미검수",
      "별표": false,
      "미분류": false,
      "인바운드": 1,
      "path": "40_시스템/ERP 시스템 · 경영자정보.md"
    },
    {
      "score": 6,
      "type": "term",
      "name": "(매입)세금계산서",
      "분류": "회계관리",
      "검수상태": "미검수",
      "별표": false,
      "미분류": false,
      "인바운드": 0,
      "path": "30_용어집/회계관리/(매입)세금계산서.md"
    },
    {
      "score": 6,
      "type": "term",
      "name": "가족수당",
      "분류": "총무관리",
      "검수상태": "미검수",
      "별표": false,
      "미분류": false,
      "인바운드": 0,
      "path": "30_용어집/총무관리/가족수당.md"
    },
    {
      "score": 6,
      "type": "term",
      "name": "거래처관리",
      "분류": "회계관리",
      "검수상태": "미검수",
      "별표": false,
      "미분류": false,
      "인바운드": 0,
      "path": "30_용어집/회계관리/거래처관리.md"
    },
    {
      "score": 6,
      "type": "term",
      "name": "검수",
      "분류": "구매관리",
      "검수상태": "미검수",
      "별표": false,
      "미분류": false,
      "인바운드": 0,
      "path": "30_용어집/구매관리/검수.md"
    },
    {
      "score": 6,
      "type": "term",
      "name": "검토실적평가",
      "분류": "평가관리",
      "검수상태": "미검수",
      "별표": false,
      "미분류": false,
      "인바운드": 0,
      "path": "30_용어집/평가관리/검토실적평가.md"
    },
    {
      "score": 6,
      "type": "term",
      "name": "결재문서",
      "분류": "공통/시스템",
      "검수상태": "미검수",
      "별표": false,
      "미분류": false,
      "인바운드": 0,
      "path": "30_용어집/공통_시스템/결재문서.md"
    },
    {
      "score": 6,
      "type": "term",
      "name": "결재상태",
      "분류": "공통/시스템",
      "검수상태": "미검수",
      "별표": false,
      "미분류": false,
      "인바운드": 0,
      "path": "30_용어집/공통_시스템/결재상태.md"
    },
    {
      "score": 6,
      "type": "term",
      "name": "경비지급의뢰서",
      "분류": "회계관리",
      "검수상태": "미검수",
      "별표": false,
      "미분류": false,
      "인바운드": 0,
      "path": "30_용어집/회계관리/경비지급의뢰서.md"
    },
    {
      "score": 6,
      "type": "term",
      "name": "계정대체",
      "분류": "회계관리",
      "검수상태": "미검수",
      "별표": false,
      "미분류": false,
      "인바운드": 0,
      "path": "30_용어집/회계관리/계정대체.md"
    },
    {
      "score": 6,
      "type": "term",
      "name": "고용형태",
      "분류": "인사관리",
      "검수상태": "미검수",
      "별표": false,
      "미분류": false,
      "인바운드": 0,
      "path": "30_용어집/인사관리/고용형태.md"
    },
    {
      "score": 6,
      "type": "term",
      "name": "공통실적항목",
      "분류": "평가관리",
      "검수상태": "미검수",
      "별표": false,
      "미분류": false,
      "인바운드": 0,
      "path": "30_용어집/평가관리/공통실적항목.md"
    },
    {
      "score": 6,
      "type": "term",
      "name": "과제번호/과제명",
      "분류": "예산관리",
      "검수상태": "미검수",
      "별표": false,
      "미분류": false,
      "인바운드": 0,
      "path": "30_용어집/예산관리/과제번호_과제명.md"
    },
    {
      "score": 6,
      "type": "term",
      "name": "교육만족도",
      "분류": "인사관리",
      "검수상태": "미검수",
      "별표": false,
      "미분류": false,
      "인바운드": 0,
      "path": "30_용어집/인사관리/교육만족도.md"
    },
    {
      "score": 6,
      "type": "term",
      "name": "구매신청",
      "분류": "구매관리",
      "검수상태": "미검수",
      "별표": false,
      "미분류": false,
      "인바운드": 0,
      "path": "30_용어집/구매관리/구매신청.md"
    },
    {
      "score": 6,
      "type": "term",
      "name": "구매진행현황",
      "분류": "구매관리",
      "검수상태": "미검수",
      "별표": false,
      "미분류": false,
      "인바운드": 0,
      "path": "30_용어집/구매관리/구매진행현황.md"
    },
    {
      "score": 6,
      "type": "term",
      "name": "국내출장",
      "분류": "복무관리",
      "검수상태": "미검수",
      "별표": false,
      "미분류": false,
      "인바운드": 0,
      "path": "30_용어집/복무관리/국내출장.md"
    },
    {
      "score": 6,
      "type": "term",
      "name": "규정집",
      "분류": "총무관리",
      "검수상태": "미검수",
      "별표": false,
      "미분류": false,
      "인바운드": 0,
      "path": "30_용어집/총무관리/규정집.md"
    },
    {
      "score": 6,
      "type": "term",
      "name": "근로소명",
      "분류": "복무관리",
      "검수상태": "미검수",
      "별표": false,
      "미분류": false,
      "인바운드": 0,
      "path": "30_용어집/복무관리/근로소명.md"
    },
    {
      "score": 6,
      "type": "term",
      "name": "근로시간관리",
      "분류": "복무관리",
      "검수상태": "미검수",
      "별표": false,
      "미분류": false,
      "인바운드": 0,
      "path": "30_용어집/복무관리/근로시간관리.md"
    },
    {
      "score": 6,
      "type": "term",
      "name": "급여명세서",
      "분류": "급여관리",
      "검수상태": "미검수",
      "별표": false,
      "미분류": false,
      "인바운드": 0,
      "path": "30_용어집/급여관리/급여명세서.md"
    },
    {
      "score": 6,
      "type": "term",
      "name": "기안",
      "분류": "공통/시스템",
      "검수상태": "미검수",
      "별표": false,
      "미분류": false,
      "인바운드": 0,
      "path": "30_용어집/공통_시스템/기안.md"
    },
    {
      "score": 6,
      "type": "term",
      "name": "마일리지현황",
      "분류": "복무관리",
      "검수상태": "미검수",
      "별표": false,
      "미분류": false,
      "인바운드": 0,
      "path": "30_용어집/복무관리/마일리지현황.md"
    },
    {
      "score": 6,
      "type": "term",
      "name": "배차",
      "분류": "총무관리",
      "검수상태": "미검수",
      "별표": false,
      "미분류": false,
      "인바운드": 0,
      "path": "30_용어집/총무관리/배차.md"
    },
    {
      "score": 6,
      "type": "term",
      "name": "법인카드 승인내역",
      "분류": "회계관리",
      "검수상태": "미검수",
      "별표": false,
      "미분류": false,
      "인바운드": 0,
      "path": "30_용어집/회계관리/법인카드 승인내역.md"
    },
    {
      "score": 6,
      "type": "term",
      "name": "복무특이자",
      "분류": "경영자정보",
      "검수상태": "미검수",
      "별표": false,
      "미분류": false,
      "인바운드": 0,
      "path": "30_용어집/경영자정보/복무특이자.md"
    },
    {
      "score": 6,
      "type": "term",
      "name": "본인인증",
      "분류": "공통/시스템",
      "검수상태": "미검수",
      "별표": false,
      "미분류": false,
      "인바운드": 0,
      "path": "30_용어집/공통_시스템/본인인증.md"
    },
    {
      "score": 6,
      "type": "term",
      "name": "부서장실적/평가",
      "분류": "평가관리",
      "검수상태": "미검수",
      "별표": false,
      "미분류": false,
      "인바운드": 0,
      "path": "30_용어집/평가관리/부서장실적_평가.md"
    },
    {
      "score": 6,
      "type": "term",
      "name": "비목",
      "분류": "예산관리",
      "검수상태": "미검수",
      "별표": false,
      "미분류": false,
      "인바운드": 0,
      "path": "30_용어집/예산관리/비목.md"
    },
    {
      "score": 6,
      "type": "term",
      "name": "사례금",
      "분류": "인사관리",
      "검수상태": "미검수",
      "별표": false,
      "미분류": false,
      "인바운드": 0,
      "path": "30_용어집/인사관리/사례금.md"
    },
    {
      "score": 6,
      "type": "term",
      "name": "사무용품신청",
      "분류": "자산관리",
      "검수상태": "미검수",
      "별표": false,
      "미분류": false,
      "인바운드": 0,
      "path": "30_용어집/자산관리/사무용품신청.md"
    },
    {
      "score": 6,
      "type": "term",
      "name": "상반기실적",
      "분류": "평가관리",
      "검수상태": "미검수",
      "별표": false,
      "미분류": false,
      "인바운드": 0,
      "path": "30_용어집/평가관리/상반기실적.md"
    },
    {
      "score": 6,
      "type": "term",
      "name": "소득공제신고서",
      "분류": "급여관리",
      "검수상태": "미검수",
      "별표": false,
      "미분류": false,
      "인바운드": 0,
      "path": "30_용어집/급여관리/소득공제신고서.md"
    },
    {
      "score": 6,
      "type": "term",
      "name": "소득자등록",
      "분류": "회계관리",
      "검수상태": "미검수",
      "별표": false,
      "미분류": false,
      "인바운드": 0,
      "path": "30_용어집/회계관리/소득자등록.md"
    },
    {
      "score": 6,
      "type": "term",
      "name": "소모품",
      "분류": "구매관리",
      "검수상태": "미검수",
      "별표": false,
      "미분류": false,
      "인바운드": 0,
      "path": "30_용어집/구매관리/소모품.md"
    },
    {
      "score": 6,
      "type": "term",
      "name": "스마트워크센터",
      "분류": "복무관리",
      "검수상태": "미검수",
      "별표": false,
      "미분류": false,
      "인바운드": 0,
      "path": "30_용어집/복무관리/스마트워크센터.md"
    },
    {
      "score": 6,
      "type": "term",
      "name": "시내출장",
      "분류": "복무관리",
      "검수상태": "미검수",
      "별표": false,
      "미분류": false,
      "인바운드": 0,
      "path": "30_용어집/복무관리/시내출장.md"
    },
    {
      "score": 6,
      "type": "term",
      "name": "실적평가",
      "분류": "평가관리",
      "검수상태": "미검수",
      "별표": false,
      "미분류": false,
      "인바운드": 0,
      "path": "30_용어집/평가관리/실적평가.md"
    },
    {
      "score": 6,
      "type": "term",
      "name": "업무추진계획",
      "분류": "평가관리",
      "검수상태": "미검수",
      "별표": false,
      "미분류": false,
      "인바운드": 0,
      "path": "30_용어집/평가관리/업무추진계획.md"
    },
    {
      "score": 6,
      "type": "term",
      "name": "엑셀다운",
      "분류": "공통/시스템",
      "검수상태": "미검수",
      "별표": false,
      "미분류": false,
      "인바운드": 0,
      "path": "30_용어집/공통_시스템/엑셀다운.md"
    },
    {
      "score": 6,
      "type": "term",
      "name": "여입",
      "분류": "회계관리",
      "검수상태": "미검수",
      "별표": false,
      "미분류": false,
      "인바운드": 0,
      "path": "30_용어집/회계관리/여입.md"
    },
    {
      "score": 6,
      "type": "term",
      "name": "역량평가",
      "분류": "평가관리",
      "검수상태": "미검수",
      "별표": false,
      "미분류": false,
      "인바운드": 0,
      "path": "30_용어집/평가관리/역량평가.md"
    },
    {
      "score": 6,
      "type": "term",
      "name": "연장근로",
      "분류": "복무관리",
      "검수상태": "미검수",
      "별표": false,
      "미분류": false,
      "인바운드": 0,
      "path": "30_용어집/복무관리/연장근로.md"
    },
    {
      "score": 6,
      "type": "term",
      "name": "연차저축제",
      "분류": "복무관리",
      "검수상태": "미검수",
      "별표": false,
      "미분류": false,
      "인바운드": 0,
      "path": "30_용어집/복무관리/연차저축제.md"
    },
    {
      "score": 6,
      "type": "term",
      "name": "예산변경",
      "분류": "예산관리",
      "검수상태": "미검수",
      "별표": false,
      "미분류": false,
      "인바운드": 0,
      "path": "30_용어집/예산관리/예산변경.md"
    },
    {
      "score": 6,
      "type": "term",
      "name": "예산집행현황",
      "분류": "예산관리",
      "검수상태": "미검수",
      "별표": false,
      "미분류": false,
      "인바운드": 0,
      "path": "30_용어집/예산관리/예산집행현황.md"
    },
    {
      "score": 6,
      "type": "term",
      "name": "예외사용자",
      "분류": "예산관리",
      "검수상태": "미검수",
      "별표": false,
      "미분류": false,
      "인바운드": 0,
      "path": "30_용어집/예산관리/예외사용자.md"
    },
    {
      "score": 6,
      "type": "term",
      "name": "원내근로시간",
      "분류": "복무관리",
      "검수상태": "미검수",
      "별표": false,
      "미분류": false,
      "인바운드": 0,
      "path": "30_용어집/복무관리/원내근로시간.md"
    },
    {
      "score": 6,
      "type": "term",
      "name": "원외겸직활동",
      "분류": "인사관리",
      "검수상태": "미검수",
      "별표": false,
      "미분류": false,
      "인바운드": 0,
      "path": "30_용어집/인사관리/원외겸직활동.md"
    },
    {
      "score": 6,
      "type": "term",
      "name": "원외근로시간",
      "분류": "복무관리",
      "검수상태": "미검수",
      "별표": false,
      "미분류": false,
      "인바운드": 0,
      "path": "30_용어집/복무관리/원외근로시간.md"
    },
    {
      "score": 6,
      "type": "term",
      "name": "원인행위",
      "분류": "회계관리",
      "검수상태": "미검수",
      "별표": false,
      "미분류": false,
      "인바운드": 0,
      "path": "30_용어집/회계관리/원인행위.md"
    },
    {
      "score": 6,
      "type": "term",
      "name": "원인행위품의",
      "분류": "회계관리",
      "검수상태": "미검수",
      "별표": false,
      "미분류": false,
      "인바운드": 0,
      "path": "30_용어집/회계관리/원인행위품의.md"
    },
    {
      "score": 6,
      "type": "term",
      "name": "위임전결규정",
      "분류": "총무관리",
      "검수상태": "미검수",
      "별표": false,
      "미분류": false,
      "인바운드": 0,
      "path": "30_용어집/총무관리/위임전결규정.md"
    },
    {
      "score": 6,
      "type": "term",
      "name": "유연근무제",
      "분류": "복무관리",
      "검수상태": "미검수",
      "별표": false,
      "미분류": false,
      "인바운드": 0,
      "path": "30_용어집/복무관리/유연근무제.md"
    },
    {
      "score": 6,
      "type": "term",
      "name": "의무시간 준수여부",
      "분류": "복무관리",
      "검수상태": "미검수",
      "별표": false,
      "미분류": false,
      "인바운드": 0,
      "path": "30_용어집/복무관리/의무시간 준수여부.md"
    },
    {
      "score": 6,
      "type": "term",
      "name": "이의신청",
      "분류": "평가관리",
      "검수상태": "미검수",
      "별표": false,
      "미분류": false,
      "인바운드": 0,
      "path": "30_용어집/평가관리/이의신청.md"
    },
    {
      "score": 6,
      "type": "term",
      "name": "일일활동보고",
      "분류": "경영지원",
      "검수상태": "미검수",
      "별표": false,
      "미분류": false,
      "인바운드": 0,
      "path": "30_용어집/경영지원/일일활동보고.md"
    },
    {
      "score": 6,
      "type": "term",
      "name": "임시직",
      "분류": "평가관리",
      "검수상태": "미검수",
      "별표": false,
      "미분류": false,
      "인바운드": 0,
      "path": "30_용어집/평가관리/임시직.md"
    },
    {
      "score": 6,
      "type": "term",
      "name": "자산반납",
      "분류": "자산관리",
      "검수상태": "미검수",
      "별표": false,
      "미분류": false,
      "인바운드": 0,
      "path": "30_용어집/자산관리/자산반납.md"
    },
    {
      "score": 6,
      "type": "term",
      "name": "자산이동",
      "분류": "자산관리",
      "검수상태": "미검수",
      "별표": false,
      "미분류": false,
      "인바운드": 0,
      "path": "30_용어집/자산관리/자산이동.md"
    },
    {
      "score": 6,
      "type": "term",
      "name": "잔표",
      "분류": "회계관리",
      "검수상태": "미검수",
      "별표": false,
      "미분류": false,
      "인바운드": 0,
      "path": "30_용어집/회계관리/잔표.md"
    },
    {
      "score": 6,
      "type": "term",
      "name": "재직구분",
      "분류": "공통/시스템",
      "검수상태": "미검수",
      "별표": false,
      "미분류": false,
      "인바운드": 0,
      "path": "30_용어집/공통_시스템/재직구분.md"
    },
    {
      "score": 6,
      "type": "term",
      "name": "재택근무",
      "분류": "복무관리",
      "검수상태": "미검수",
      "별표": false,
      "미분류": false,
      "인바운드": 0,
      "path": "30_용어집/복무관리/재택근무.md"
    },
    {
      "score": 6,
      "type": "term",
      "name": "적요",
      "분류": "공통/시스템",
      "검수상태": "미검수",
      "별표": false,
      "미분류": false,
      "인바운드": 0,
      "path": "30_용어집/공통_시스템/적요.md"
    },
    {
      "score": 6,
      "type": "term",
      "name": "전직원 연구행정 가이드",
      "분류": "총무관리",
      "검수상태": "미검수",
      "별표": false,
      "미분류": false,
      "인바운드": 0,
      "path": "30_용어집/총무관리/전직원 연구행정 가이드.md"
    },
    {
      "score": 6,
      "type": "term",
      "name": "제증명",
      "분류": "인사관리",
      "검수상태": "미검수",
      "별표": false,
      "미분류": false,
      "인바운드": 0,
      "path": "30_용어집/인사관리/제증명.md"
    },
    {
      "score": 6,
      "type": "term",
      "name": "주간업무보고",
      "분류": "경영지원",
      "검수상태": "미검수",
      "별표": false,
      "미분류": false,
      "인바운드": 0,
      "path": "30_용어집/경영지원/주간업무보고.md"
    },
    {
      "score": 6,
      "type": "term",
      "name": "지급신청서",
      "분류": "회계관리",
      "검수상태": "미검수",
      "별표": false,
      "미분류": false,
      "인바운드": 0,
      "path": "30_용어집/회계관리/지급신청서.md"
    },
    {
      "score": 6,
      "type": "term",
      "name": "직급/직책/직무",
      "분류": "인사관리",
      "검수상태": "미검수",
      "별표": false,
      "미분류": false,
      "인바운드": 0,
      "path": "30_용어집/인사관리/직급_직책_직무.md"
    },
    {
      "score": 6,
      "type": "term",
      "name": "청산기간",
      "분류": "복무관리",
      "검수상태": "미검수",
      "별표": false,
      "미분류": false,
      "인바운드": 0,
      "path": "30_용어집/복무관리/청산기간.md"
    },
    {
      "score": 6,
      "type": "term",
      "name": "청원휴가",
      "분류": "복무관리",
      "검수상태": "미검수",
      "별표": false,
      "미분류": false,
      "인바운드": 0,
      "path": "30_용어집/복무관리/청원휴가.md"
    },
    {
      "score": 6,
      "type": "term",
      "name": "최종평가결과",
      "분류": "평가관리",
      "검수상태": "미검수",
      "별표": false,
      "미분류": false,
      "인바운드": 0,
      "path": "30_용어집/평가관리/최종평가결과.md"
    },
    {
      "score": 6,
      "type": "term",
      "name": "추가증빙",
      "분류": "회계관리",
      "검수상태": "미검수",
      "별표": false,
      "미분류": false,
      "인바운드": 0,
      "path": "30_용어집/회계관리/추가증빙.md"
    },
    {
      "score": 6,
      "type": "term",
      "name": "출장유형(해외)",
      "분류": "복무관리",
      "검수상태": "미검수",
      "별표": false,
      "미분류": false,
      "인바운드": 0,
      "path": "30_용어집/복무관리/출장유형(해외).md"
    },
    {
      "score": 6,
      "type": "term",
      "name": "출장정산",
      "분류": "복무관리",
      "검수상태": "미검수",
      "별표": false,
      "미분류": false,
      "인바운드": 0,
      "path": "30_용어집/복무관리/출장정산.md"
    },
    {
      "score": 6,
      "type": "term",
      "name": "콘도",
      "분류": "총무관리",
      "검수상태": "미검수",
      "별표": false,
      "미분류": false,
      "인바운드": 0,
      "path": "30_용어집/총무관리/콘도.md"
    },
    {
      "score": 6,
      "type": "term",
      "name": "통제금액",
      "분류": "회계관리",
      "검수상태": "미검수",
      "별표": false,
      "미분류": false,
      "인바운드": 0,
      "path": "30_용어집/회계관리/통제금액.md"
    },
    {
      "score": 6,
      "type": "term",
      "name": "퇴직금중간정산",
      "분류": "급여관리",
      "검수상태": "미검수",
      "별표": false,
      "미분류": false,
      "인바운드": 0,
      "path": "30_용어집/급여관리/퇴직금중간정산.md"
    },
    {
      "score": 6,
      "type": "term",
      "name": "포상훈격",
      "분류": "인사관리",
      "검수상태": "미검수",
      "별표": false,
      "미분류": false,
      "인바운드": 0,
      "path": "30_용어집/인사관리/포상훈격.md"
    },
    {
      "score": 6,
      "type": "term",
      "name": "품의",
      "분류": "회계관리",
      "검수상태": "미검수",
      "별표": false,
      "미분류": false,
      "인바운드": 0,
      "path": "30_용어집/회계관리/품의.md"
    },
    {
      "score": 6,
      "type": "term",
      "name": "해외출장",
      "분류": "복무관리",
      "검수상태": "미검수",
      "별표": false,
      "미분류": false,
      "인바운드": 0,
      "path": "30_용어집/복무관리/해외출장.md"
    },
    {
      "score": 6,
      "type": "term",
      "name": "행정관리시스템(ERP)",
      "분류": "공통/시스템",
      "검수상태": "미검수",
      "별표": false,
      "미분류": false,
      "인바운드": 0,
      "path": "30_용어집/공통_시스템/행정관리시스템(ERP).md"
    },
    {
      "score": 6,
      "type": "term",
      "name": "현업적용도평가",
      "분류": "인사관리",
      "검수상태": "미검수",
      "별표": false,
      "미분류": false,
      "인바운드": 0,
      "path": "30_용어집/인사관리/현업적용도평가.md"
    },
    {
      "score": 6,
      "type": "term",
      "name": "환급여부",
      "분류": "인사관리",
      "검수상태": "미검수",
      "별표": false,
      "미분류": false,
      "인바운드": 0,
      "path": "30_용어집/인사관리/환급여부.md"
    },
    {
      "score": 6,
      "type": "term",
      "name": "휴가촉진",
      "분류": "복무관리",
      "검수상태": "미검수",
      "별표": false,
      "미분류": false,
      "인바운드": 0,
      "path": "30_용어집/복무관리/휴가촉진.md"
    }
  ]
}